capture/__init__.py
capture/__main__.py
capture/app.py
capture/bam.py
capture/clean.py
capture/jobs.py
capture/join.py
capture/parse.py
capture/run.py
capture/split.py
capture/version.py
capture/test/test_bam.py
capture/test/test_clean.py
capture/test/test_join.py
capture/test/test_parse.py
capture/test/test_parse_random.py
capture/test/test_run.py
capture_assembler-0.1.0.dist-info/METADATA
capture_assembler-0.1.0.dist-info/RECORD
capture_assembler-0.1.0.dist-info/WHEEL
capture_assembler-0.1.0.dist-info/entry_points.txt
capture_assembler-0.1.0.dist-info/top_level.txt
