Metadata-Version: 2.1
Name: capture-assembler
Version: 0.1.0
Summary: The Capture seq assembler
Home-page: https://github.com/SGBC/capture
Author: Hadrien Gourlé, Renaud Van Damme
Author-email: hadrien.gourle@slu.se
License: MIT
Download-URL: https://github.com/SGBC/capture/tarball/0.1.0
Platform: UNKNOWN
Requires-Dist: doit
Requires-Dist: biopython
Requires-Dist: pysam
